{
  "charts": [],
  "content": "[{\"type\":\"header\",\"data\":{\"text\":\"Budgets\"}}]",
  "creation": "2023-05-31 09:01:28.994484",
  "docstatus": 0,
  "doctype": "Workspace",
  "for_user": "",
  "hide_custom": 0,
  "icon": "loan",
  "idx": 0,
  "is_hidden": 0,
  "is_standard": 1,
  "label": "Budgets",
  "links": [],
  "modified": "2023-05-31 09:05:59.534241",
  "modified_by": "Administrator",
  "module": "Accounts",
  "name": "Budgets",
  "number_cards": [],
  "owner": "Administrator",
  "parent_page": "Finance",
  "public": 1,
  "quick_lists": [],
  "roles": [],
  "sequence_id": 5.0,
  "shortcuts": [],
  "title": "Budgets"
}
